vollseg_napari_trackmate/__init__.py
vollseg_napari_trackmate/_data_model.py
vollseg_napari_trackmate/_sample_data.py
vollseg_napari_trackmate/_temporal_plots.py
vollseg_napari_trackmate/_version.py
vollseg_napari_trackmate/_widget.py
vollseg_napari_trackmate/launch.py
vollseg_napari_trackmate/napari.yaml
vollseg_napari_trackmate/_tests/__init__.py
vollseg_napari_trackmate/_tests/test_reader.py
vollseg_napari_trackmate/_tests/test_sample_data.py
vollseg_napari_trackmate/_tests/test_widget.py
vollseg_napari_trackmate/_tests/test_writer.py
vollseg_napari_trackmate/resources/kapoorlogo.png
vollseg_napari_trackmate-2.6.7.dist-info/licenses/LICENSE
vollseg_napari_trackmate-2.6.7.dist-info/METADATA
vollseg_napari_trackmate-2.6.7.dist-info/WHEEL
vollseg_napari_trackmate-2.6.7.dist-info/entry_points.txt
vollseg_napari_trackmate-2.6.7.dist-info/top_level.txt
vollseg_napari_trackmate-2.6.7.dist-info/RECORD
