Metadata-Version: 2.4
Name: vollseg-napari-trackmate
Version: 2.6.7
Summary: Track analysis using TrackMate xml and csv generated tracks using NapaTrackMater as the base library
Home-page: https://github.com/Kapoorlabs-CAPED/vollseg-napari-trackmate
Author: Varun Kapoor, Mari Tolonen, Jakub Sedzinski
Author-email: randomaccessiblekapoor@gmail.com
License: BSD-3-Clause
Project-URL: Bug Tracker, https://github.com/Kapoorlabs-CAPED/vollseg-napari-trackmate/issues
Project-URL: Documentation, https://github.com/Kapoorlabs-CAPED/vollseg-napari-trackmate#README.md
Project-URL: Source Code, https://github.com/Kapoorlabs-CAPED/vollseg-napari-trackmate
Project-URL: User Support, https://github.com/Kapoorlabs-CAPED/vollseg-napari-trackmate/issues
Classifier: Development Status :: 2 - Pre-Alpha
Classifier: Framework :: napari
Classifier: Intended Audience :: Developers
Classifier: License :: OSI Approved :: BSD License
Classifier: Operating System :: OS Independent
Classifier: Programming Language :: Python
Classifier: Programming Language :: Python :: 3
Classifier: Programming Language :: Python :: 3 :: Only
Classifier: Programming Language :: Python :: 3.8
Classifier: Programming Language :: Python :: 3.9
Classifier: Programming Language :: Python :: 3.10
Classifier: Topic :: Scientific/Engineering :: Image Processing
Requires-Python: >=3.8
License-File: LICENSE
Requires-Dist: napari-plugin-engine>=0.1.4
Requires-Dist: caped-ai
Provides-Extra: testing
Requires-Dist: tox; extra == "testing"
Requires-Dist: pytest; extra == "testing"
Requires-Dist: pytest-cov; extra == "testing"
Requires-Dist: pytest-qt; extra == "testing"
Requires-Dist: napari; extra == "testing"
Requires-Dist: pyqt5; extra == "testing"
Dynamic: license-file
